luxfhe/__init__.py
luxfhe/core.py
luxfhe-1.2.0.dist-info/METADATA
luxfhe-1.2.0.dist-info/WHEEL
luxfhe-1.2.0.dist-info/top_level.txt
luxfhe-1.2.0.dist-info/RECORD
