Metadata-Version: 2.4
Name: luxfhe
Version: 1.2.0
Summary: Python bindings for LuxFHE - Fully Homomorphic Encryption
Author-email: Lux Industries Inc <dev@lux.industries>
License: BSD-3-Clause
Project-URL: Homepage, https://github.com/luxfi/fhe
Project-URL: Documentation, https://fhe.lux.dev
Project-URL: Repository, https://github.com/luxfi/fhe
Project-URL: Changelog, https://github.com/luxfi/fhe/blob/main/CHANGELOG.md
Keywords: fhe,fhe,homomorphic-encryption,cryptography,privacy,blockchain
Classifier: Development Status :: 4 - Beta
Classifier: Intended Audience :: Developers
Classifier: Intended Audience :: Science/Research
Classifier: License :: OSI Approved :: BSD License
Classifier: Operating System :: OS Independent
Classifier: Programming Language :: Python :: 3
Classifier: Programming Language :: Python :: 3.9
Classifier: Programming Language :: Python :: 3.10
Classifier: Programming Language :: Python :: 3.11
Classifier: Programming Language :: Python :: 3.12
Classifier: Topic :: Security :: Cryptography
Classifier: Topic :: Software Development :: Libraries :: Python Modules
Requires-Python: >=3.9
Requires-Dist: cffi>=1.0
Provides-Extra: dev
Requires-Dist: pytest>=7.0; extra == "dev"
Requires-Dist: pytest-cov>=4.0; extra == "dev"
Requires-Dist: black>=23.0; extra == "dev"
Requires-Dist: ruff>=0.1.0; extra == "dev"
Requires-Dist: mypy>=1.0; extra == "dev"
